metapub/__init__.py
metapub/base.py
metapub/cache_utils.py
metapub/cite.py
metapub/clinvarfetcher.py
metapub/clinvarvariant.py
metapub/config.py
metapub/convert.py
metapub/crossref.py
metapub/dx_doi.py
metapub/eutils_common.py
metapub/exceptions.py
metapub/medgenconcept.py
metapub/medgenfetcher.py
metapub/ncbi_errors.py
metapub/ncbi_health_check.py
metapub/pubmed_clinicalqueries.py
metapub/pubmedarticle.py
metapub/pubmedauthor.py
metapub/pubmedcentral.py
metapub/pubmedfetcher.py
metapub/pubmedfetcher_cli.py
metapub/text_mining.py
metapub/utils.py
metapub/validate.py
metapub/findit/__init__.py
metapub/findit/dances.py
metapub/findit/findit.py
metapub/findit/logic.py
metapub/findit/journals/__init__.py
metapub/findit/journals/aaas.py
metapub/findit/journals/biochemsoc.py
metapub/findit/journals/bmc.py
metapub/findit/journals/cantdo_list.py
metapub/findit/journals/cell.py
metapub/findit/journals/degruyter.py
metapub/findit/journals/dustri.py
metapub/findit/journals/endo.py
metapub/findit/journals/jama.py
metapub/findit/journals/jstage.py
metapub/findit/journals/karger.py
metapub/findit/journals/lancet.py
metapub/findit/journals/misc_doi.py
metapub/findit/journals/misc_pii.py
metapub/findit/journals/misc_vip.py
metapub/findit/journals/nature.py
metapub/findit/journals/paywalled.py
metapub/findit/journals/scielo.py
metapub/findit/journals/sciencedirect.py
metapub/findit/journals/spandidos.py
metapub/findit/journals/springer.py
metapub/findit/journals/todo.py
metapub/findit/journals/wiley.py
metapub/findit/journals/wolterskluwer.py
metapub/urlreverse/__init__.py
metapub/urlreverse/hostname2doiprefix.py
metapub/urlreverse/hostname2jrnl.py
metapub/urlreverse/methods.py
metapub/urlreverse/urlreverse.py
metapub-0.6.3.dist-info/licenses/LICENSE
metapub-0.6.3.dist-info/licenses/LICENSE-2.0.txt
tests/DEACTIVATED_test_urlreverse.py
tests/__init__.py
tests/common.py
tests/conftest.py
tests/test_asciify.py
tests/test_base.py
tests/test_bibtex_citation.py
tests/test_citation_formatting.py
tests/test_citation_html_regression.py
tests/test_clinvar_fetcher.py
metapub-0.6.3.dist-info/METADATA
metapub-0.6.3.dist-info/WHEEL
metapub-0.6.3.dist-info/entry_points.txt
metapub-0.6.3.dist-info/top_level.txt
metapub-0.6.3.dist-info/RECORD
