Metadata-Version: 2.4
Name: metapub
Version: 0.6.3
Summary: Pubmed / NCBI / eutils interaction library, handling the metadata of pubmed papers.
Home-page: https://github.com/metapub/metapub
Author: Naomi Most
Author-email: naomi@nthmost.com
Maintainer: Naomi Most
Maintainer-email: naomi@nthmost.com
License: Apache 2.0
License-File: LICENSE
License-File: LICENSE-2.0.txt
Requires-Dist: setuptools
Requires-Dist: lxml
Requires-Dist: lxml_html_clean
Requires-Dist: requests
Requires-Dist: eutils
Requires-Dist: habanero
Requires-Dist: tabulate
Requires-Dist: cssselect
Requires-Dist: unidecode
Requires-Dist: docopt
Requires-Dist: six
Requires-Dist: coloredlogs
Requires-Dist: python-Levenshtein
Provides-Extra: test
Requires-Dist: tox; extra == "test"
Requires-Dist: pytest; extra == "test"
Dynamic: author
Dynamic: author-email
Dynamic: description
Dynamic: description-content-type
Dynamic: home-page
Dynamic: license
Dynamic: license-file
Dynamic: maintainer
Dynamic: maintainer-email
Dynamic: provides-extra
Dynamic: requires-dist
Dynamic: summary
